gitwho/__init__.py
gitwho-0.0.0.dist-info/METADATA
gitwho-0.0.0.dist-info/WHEEL
gitwho-0.0.0.dist-info/RECORD
