Metadata-Version: 2.1
Name: gitwho
Version: 0.0.0
Summary: A CLI tool to collect names of authors and committers for a Git org.
Author: Leron Gray
Author-email: daddycocoaman@gmail.com
Requires-Python: >=3.11,<4.0
Classifier: Programming Language :: Python :: 3
Classifier: Programming Language :: Python :: 3.11
Classifier: Programming Language :: Python :: 3.12
